[{"Employee ID":1,"Name":"Alice","Age":29,"Department":"HR","Salary":50000.0,"Start Date":"2023-05-21"},{"Employee ID":2,"Name":"Bob","Age":34,"Department":"Engineering","Salary":75000.0,"Start Date":"2019-08-14"},{"Employee ID":3,"Name":"Charlie","Age":31,"Department":"Finance","Salary":null,"Start Date":"2021-01-10"},{"Employee ID":4,"Name":"David","Age":28,"Department":"HR","Salary":null,"Start Date":"2018-11-03"},{"Employee ID":5,"Name":"Eve","Age":42,"Department":"Finance","Salary":85000.0,"Start Date":"2022-06-27"}]